LICENSE
MANIFEST.in
README.md
pyproject.toml
requirements.txt
setup.py
syntheticstellarpopconvolve/SFR_dict_plotting_routines.py
syntheticstellarpopconvolve/__init__.py
syntheticstellarpopconvolve/_version.py
syntheticstellarpopconvolve/archive.py
syntheticstellarpopconvolve/calculate_birth_redshift_array.py
syntheticstellarpopconvolve/calculate_starformation_rate.py
syntheticstellarpopconvolve/check_and_prepare_output_file.py
syntheticstellarpopconvolve/check_and_update_convolution_config.py
syntheticstellarpopconvolve/check_and_update_convolution_instruction.py
syntheticstellarpopconvolve/check_and_update_sfr_dict.py
syntheticstellarpopconvolve/convolution_by_integration.py
syntheticstellarpopconvolve/convolution_by_sampling.py
syntheticstellarpopconvolve/convolve.py
syntheticstellarpopconvolve/convolve_binned_data.py
syntheticstellarpopconvolve/convolve_ensembles.py
syntheticstellarpopconvolve/convolve_on_the_fly.py
syntheticstellarpopconvolve/convolve_populations.py
syntheticstellarpopconvolve/convolve_pre_calculated_data.py
syntheticstellarpopconvolve/cosmology_utils.py
syntheticstellarpopconvolve/default_convolution_config.py
syntheticstellarpopconvolve/default_convolution_instruction.py
syntheticstellarpopconvolve/docs.py
syntheticstellarpopconvolve/ensemble_utils.py
syntheticstellarpopconvolve/functions_to_review.py
syntheticstellarpopconvolve/general_functions.py
syntheticstellarpopconvolve/metallicity_distributions.py
syntheticstellarpopconvolve/post_convolution_hook_routines.py
syntheticstellarpopconvolve/prepare_redshift_interpolator.py
syntheticstellarpopconvolve/starformation_rate_distributions.py
syntheticstellarpopconvolve/store_redshift_shell_info.py
syntheticstellarpopconvolve.egg-info/PKG-INFO
syntheticstellarpopconvolve.egg-info/SOURCES.txt
syntheticstellarpopconvolve.egg-info/dependency_links.txt
syntheticstellarpopconvolve.egg-info/requires.txt
syntheticstellarpopconvolve.egg-info/top_level.txt
syntheticstellarpopconvolve/example_data/example_BinCodex.h5
syntheticstellarpopconvolve/example_data/example_BinCodex_dwd.h5
syntheticstellarpopconvolve/example_data/example_RLOF_event_data.dat
syntheticstellarpopconvolve/example_data/example_data_usecase_gw.h5
