Metadata-Version: 2.1
Name: syntheticstellarpopconvolve
Version: 0.4
Summary: synthetic stellar pop convolve is a python package to convolve output of stellar population synthesis codes with star formation rates.
Home-page: https://gitlab.com/dhendriks/syntheticstellarpopconvolve
Author: David Hendriks
Author-email: davidhendriks93@gmail.com
License: gpl
Project-URL: Documentation, https://synthetic-stellar-pop-convolve.readthedocs.io/en/latest/
Project-URL: Source, https://gitlab.com/dhendriks/syntheticstellarpopconvolve
Project-URL: Bug Tracker, https://gitlab.com/dhendriks/syntheticstellarpopconvolve/-/issues
Keywords: astrophysics,stellar evolution,population synthesis,starformation rate history,convolution
Platform: UNKNOWN
Classifier: Development Status :: 4 - Beta
Classifier: License :: OSI Approved :: GNU General Public License v3 or later (GPLv3+)
Classifier: Intended Audience :: Developers
Classifier: Intended Audience :: Science/Research
Classifier: Operating System :: POSIX :: Linux
Classifier: Programming Language :: Python :: 3
Classifier: Programming Language :: C
Classifier: Topic :: Education
Classifier: Topic :: Scientific/Engineering :: Astronomy
Classifier: Topic :: Scientific/Engineering :: Physics
Classifier: Topic :: Software Development :: Libraries :: Python Modules
License-File: LICENSE
